vedro_dependency_finder/__init__.py
vedro_dependency_finder/_dependency_finder.py
vedro_dependency_finder/_dependency_scheduler.py
vedro_dependency_finder/_generate_sequence_of_indexes.py
vedro_dependency_finder/_get_indexes_of_scenarios.py
vedro_dependency_finder/py.typed
vedro_dependency_finder-0.1.1.dist-info/METADATA
vedro_dependency_finder-0.1.1.dist-info/WHEEL
vedro_dependency_finder-0.1.1.dist-info/top_level.txt
vedro_dependency_finder-0.1.1.dist-info/RECORD
