Metadata-Version: 2.1
Name: vedro-dependency-finder
Version: 0.1.1
Summary: Plugin helps to find dependencies of unstable tests by shuffling selected tests
Home-page: https://github.com/TeoDV/vedro-dependency-finder/
Author: Daria Cherepakhina
Author-email: da19sha96@yandex.ru
Classifier: Programming Language :: Python :: 3.8
Classifier: Programming Language :: Python :: 3.9
Classifier: Programming Language :: Python :: 3.10
Classifier: Typing :: Typed
Requires-Python: >=3.8
Requires-Dist: vedro <2.0,>=1.7
